iouopt/__init__.py
iouopt/flow.py
iouopt/journal.py
iouopt/py.typed
iouopt-0.2.0.dist-info/LICENSE
iouopt-0.2.0.dist-info/METADATA
iouopt-0.2.0.dist-info/WHEEL
iouopt-0.2.0.dist-info/top_level.txt
iouopt-0.2.0.dist-info/RECORD
