Metadata-Version: 2.1
Name: iouopt
Version: 0.2.0
Summary: Simplify group IOU settlement.
License: MIT License
Project-URL: Homepage, https://github.com/invisiblefunnel/iouopt
Project-URL: Issues, https://github.com/invisiblefunnel/iouopt/issues
Requires-Python: >=3.8
License-File: LICENSE
Requires-Dist: ortools
Provides-Extra: ci
Requires-Dist: black ; extra == 'ci'
Requires-Dist: isort ; extra == 'ci'
Requires-Dist: mypy ; extra == 'ci'
